staticfiles_downloader/__init__.py
django_staticfiles_downloader-1.0.0.dist-info/LICENSE
django_staticfiles_downloader-1.0.0.dist-info/WHEEL
django_staticfiles_downloader-1.0.0.dist-info/METADATA
django_staticfiles_downloader-1.0.0.dist-info/RECORD
