Metadata-Version: 2.1
Name: django-staticfiles-downloader
Version: 1.0.0
Summary: Django staticfiles extension to download third-party static files
Home-page: https://github.com/misli/django-staticfiles-downloader
License: BSD-3-Clause
Author: Jakub Dorňák
Author-email: jakub.dornak@misli.cz
Requires-Python: >=3.6,<4
Classifier: Development Status :: 5 - Production/Stable
Classifier: Environment :: Web Environment
Classifier: Framework :: Django
Classifier: Framework :: Django :: 3.1
Classifier: Intended Audience :: Developers
Classifier: License :: OSI Approved :: BSD License
Classifier: Natural Language :: English
Classifier: Operating System :: OS Independent
Classifier: Programming Language :: Python
Classifier: Programming Language :: Python :: 3
Classifier: Programming Language :: Python :: 3.6
Classifier: Programming Language :: Python :: 3.7
Classifier: Programming Language :: Python :: 3.8
Classifier: Programming Language :: Python :: 3.9
Requires-Dist: Django (>=3.0,<4)
Project-URL: Repository, https://github.com/misli/django-staticfiles-downloader
